ugetcli/__init__.py
ugetcli/__main__.py
ugetcli/cli.py
ugetcli/csproj.py
ugetcli/msbuild.py
ugetcli/nuget.py
ugetcli/nuspec.py
ugetcli/uget.py
ugetcli/unitypackage.py
ugetcli/utils.py
ugetcli-0.4.2.dist-info/AUTHORS.rst
ugetcli-0.4.2.dist-info/LICENSE
ugetcli-0.4.2.dist-info/METADATA
ugetcli-0.4.2.dist-info/WHEEL
ugetcli-0.4.2.dist-info/entry_points.txt
ugetcli-0.4.2.dist-info/top_level.txt
ugetcli-0.4.2.dist-info/RECORD
