Metadata-Version: 2.1
Name: ugetcli
Version: 0.4.2
Summary: uGet Command Line Interface
Home-page: https://github.com/AgeOfLearning/ugetcli
Author: Leonid Umanskiy
Author-email: leonid.umanskiy@aofl.com
License: MIT
Keywords: ugetcli
Platform: UNKNOWN
Classifier: Development Status :: 2 - Pre-Alpha
Classifier: Intended Audience :: Developers
Classifier: License :: OSI Approved :: BSD License
Classifier: Natural Language :: English
Classifier: Programming Language :: Python :: 2
Classifier: Programming Language :: Python :: 2.7
Classifier: Programming Language :: Python :: 3
Classifier: Programming Language :: Python :: 3.4
Classifier: Programming Language :: Python :: 3.5
Classifier: Programming Language :: Python :: 3.6
Classifier: Programming Language :: Python :: 3.7
Requires-Dist: Click (>=6.0)
Requires-Dist: upackage (>=0.1.6)
